monobit/__init__.py
monobit/constants.py
monobit/base/__init__.py
monobit/base/basetypes.py
monobit/base/binary.py
monobit/base/cachedprops.py
monobit/base/imports.py
monobit/base/properties.py
monobit/base/struct.py
monobit/core/__init__.py
monobit/core/font.py
monobit/core/glyph.py
monobit/core/labels.py
monobit/core/pack.py
monobit/core/raster.py
monobit/core/vector.py
monobit/encoding/__init__.py
monobit/encoding/base.py
monobit/encoding/charmaps.py
monobit/encoding/definitions.py
monobit/encoding/indexers.py
monobit/encoding/registry.py
monobit/encoding/taggers.py
monobit/encoding/unicode.py
monobit/encoding/tables/__init__.py
monobit/encoding/tables/charmaps.json
monobit/encoding/tables/adobe/README.md
monobit/encoding/tables/adobe/ReadMe.txt
monobit/encoding/tables/adobe/stdenc.txt
monobit/encoding/tables/adobe/symbol.txt
monobit/encoding/tables/adobe/zdingbat.txt
monobit/encoding/tables/agl/LICENSE.md
monobit/encoding/tables/agl/README.md
monobit/encoding/tables/agl/aglfn.txt
monobit/encoding/tables/agl/glyphlist.txt
monobit/encoding/tables/apple/ARABIC.TXT
monobit/encoding/tables/apple/CELTIC.TXT
monobit/encoding/tables/apple/CENTEURO.TXT
monobit/encoding/tables/apple/CHINSIMP.TXT
monobit/encoding/tables/apple/CHINTRAD.TXT
monobit/encoding/tables/apple/CORPCHAR.TXT
monobit/encoding/tables/apple/CROATIAN.TXT
monobit/encoding/tables/apple/CYRILLIC.TXT
monobit/encoding/tables/apple/DEVANAGA.TXT
monobit/encoding/tables/apple/DINGBATS.TXT
monobit/encoding/tables/apple/FARSI.TXT
monobit/encoding/tables/apple/GAELIC.TXT
monobit/encoding/tables/apple/GREEK.TXT
monobit/encoding/tables/apple/GUJARATI.TXT
monobit/encoding/tables/apple/GURMUKHI.TXT
monobit/encoding/tables/apple/HEBREW.TXT
monobit/encoding/tables/apple/ICELAND.TXT
monobit/encoding/tables/apple/INUIT.TXT
monobit/encoding/tables/apple/JAPANESE.TXT
monobit/encoding/tables/apple/KEYBOARD.TXT
monobit/encoding/tables/apple/KOREAN.TXT
monobit/encoding/tables/apple/README.md
monobit-0.48.0.dist-info/METADATA
monobit-0.48.0.dist-info/WHEEL
monobit-0.48.0.dist-info/entry_points.txt
monobit-0.48.0.dist-info/licenses/LICENSE
monobit-0.48.0.dist-info/RECORD
