Metadata-Version: 2.3
Name: monobit
Version: 0.48.0
Summary: Tools for working with monochrome bitmap fonts.
Project-URL: Homepage, https://github.com/robhagemans/monobit
Author-email: Rob Hagemans <rob.hagemans@hotmail.com>
License: MIT License
License-File: LICENSE
Keywords: 8-bit,bitfont,bitmap-font,font,pixel-font,retro
Classifier: Development Status :: 4 - Beta
Classifier: Intended Audience :: Developers
Classifier: License :: OSI Approved :: MIT License
Classifier: Programming Language :: Python :: 3.9
Requires-Python: >=3.9
Requires-Dist: acefile
Requires-Dist: arabic-reshaper
Requires-Dist: fonttools
Requires-Dist: libarchive-c
Requires-Dist: ncompress
Requires-Dist: pillow
Requires-Dist: python-bidi
Requires-Dist: reportlab
Requires-Dist: uniseg
